{
  "category": "refactor",
  "description": "Structure the application as a modular monolith with clear module boundaries and APIs, where each module (e.g., Documents, Relationships, AI) can communicate only through defined interfaces, preparing for potential future microservices extraction.\n\n**Rationale:** This provides microservices benefits (modularity, clear boundaries, independent testing) without operational complexity. It enables gradual evolution to distributed architecture if needed while maintaining current deployment simplicity and avoiding premature distribution.",
  "title": "Build a Modular Monolith with Internal Service Boundaries",
  "status": "completed",
  "id": "feature-1768328164861-1r9i9b7zm",
  "descriptionHistory": [
    {
      "description": "Structure the application as a modular monolith with clear module boundaries and APIs, where each module (e.g., Documents, Relationships, AI) can communicate only through defined interfaces, preparing for potential future microservices extraction.\n\n**Rationale:** This provides microservices benefits (modularity, clear boundaries, independent testing) without operational complexity. It enables gradual evolution to distributed architecture if needed while maintaining current deployment simplicity and avoiding premature distribution.",
      "timestamp": "2026-01-13T18:16:04.861Z",
      "source": "initial"
    }
  ],
  "branchName": "main",
  "startedAt": "2026-01-13T19:13:46.811Z",
  "updatedAt": "2026-01-13T19:28:58.994Z"
}
